fidedu/__init__.py
fidedu/__main__.py
fidedu/cli.py
fidedu/core.py
fidedu-2.1.0.dist-info/licenses/LICENSE
fidedu-2.1.0.dist-info/METADATA
fidedu-2.1.0.dist-info/WHEEL
fidedu-2.1.0.dist-info/entry_points.txt
fidedu-2.1.0.dist-info/top_level.txt
fidedu-2.1.0.dist-info/RECORD
