Metadata-Version: 2.4
Name: fidedu
Version: 2.1.0
Summary: In-place hardlink deduplication across one or more folders.
Author: Kevin Veen-Birkenbach
License: MIT
Project-URL: Homepage, https://github.com/kevinveenbirkenbach/file-dedupe
Project-URL: Repository, https://github.com/kevinveenbirkenbach/file-dedupe
Project-URL: Issues, https://github.com/kevinveenbirkenbach/file-dedupe/issues
Keywords: dedupe,hardlink,filesystem,blake2,in-place
Classifier: Programming Language :: Python :: 3
Classifier: License :: OSI Approved :: MIT License
Classifier: Operating System :: POSIX :: Linux
Classifier: Topic :: System :: Filesystems
Classifier: Topic :: Utilities
Requires-Python: >=3.9
License-File: LICENSE
Dynamic: license-file
